envOS/__init__.py
envOS/server.py
envOS-0.0.7.dist-info/LICENSE
envOS-0.0.7.dist-info/METADATA
envOS-0.0.7.dist-info/WHEEL
envOS-0.0.7.dist-info/top_level.txt
envOS-0.0.7.dist-info/RECORD
