Metadata-Version: 2.1
Name: envOS
Version: 0.0.7
Summary: Obtiene las variables de entorno, para tener mantenimientos eficientes
Home-page: https://gitwell.gwldx.com:2443/python_libraries/envOS.git
Author: Pedro Jesús Pérez Hernández
Author-email: pedrojesus.perez@welldex.mx
License: MIT
License-File: LICENSE
